firebirdsql_run/__init__.py
firebirdsql_run/main.py
firebirdsql_run/type.py
firebirdsql_run/util.py
firebirdsql_run-1.2.1.dist-info/METADATA
firebirdsql_run-1.2.1.dist-info/WHEEL
firebirdsql_run-1.2.1.dist-info/licenses/LICENSE
firebirdsql_run-1.2.1.dist-info/RECORD
