Metadata-Version: 2.4
Name: firebirdsql-run
Version: 1.2.1
Summary: Firebirdsql wrapper inspired by subprocess.run
Project-URL: Repository, https://github.com/deadnews/firebirdsql-run
Project-URL: Changelog, https://github.com/deadnews/firebirdsql-run/CHANGELOG.md
Project-URL: Documentation, https://deadnews.github.io/firebirdsql-run
Author-email: deadnews <deadnewsgit@gmail.com>
License-Expression: MIT
License-File: LICENSE
Keywords: api,firebird,sql
Classifier: Operating System :: OS Independent
Classifier: Topic :: Database
Requires-Python: >=3.10
Requires-Dist: firebirdsql==1.4.1
Requires-Dist: passlib>=1.7.4
